onion/__init__.py
onion/onion.py
onion/onion_meta.py
onion_arch-0.4.2.dist-info/METADATA
onion_arch-0.4.2.dist-info/WHEEL
onion_arch-0.4.2.dist-info/top_level.txt
onion_arch-0.4.2.dist-info/RECORD
